{
    "title": [
        {
            "start": 1,
            "end": 109,
            "text": "The Design and Implementation of a Broadly Applicable Algorithm for Optimizing Intra-Day Surgical Scheduling"
        },
        {
            "start": 1100,
            "end": 1208,
            "text": "The Design and Implementation of a Broadly Applicable Algorithm for Optimizing Intra-Day Surgical Scheduling"
        }
    ],
    "abstract": [
        {
            "start": 1359,
            "end": 2945,
            "text": "† These authors contributed equally to this work.AbstractSurgical scheduling optimization is an active area of research. However, few algorithms to optimize surgical scheduling are implemented and see sustained use. An algorithm is more likely to be implemented, if it allows for surgeon autonomy, i.e., requires only limited scheduling centralization, and functions in the limited technical infrastructure of widely used electronic medical records (EMRs). In order for an algorithm to see sustained use it must be compatible with changes to hospital capacity, patient volumes, and scheduling practices. To meet these objectives, we developed the BEDS (better elective day of surgery) algorithm, a greedy heuristic for smoothing unit-specific surgical admissions across days. We implemented BEDS in the EMR of a large pediatric academic medical center. The use of BEDS was associated with a reduction in the variability in the number of admissions. BEDS is freely available as a dashboard in Tableau, a commercial software used by numerous hospitals. BEDS is readily implementable with the limited tools available to most hospitals, does not require reductions to surgeon autonomy or centralized scheduling, and is compatible with changes to hospital capacity or patient volumes. We present a general algorithmic framework from which BEDS is derived based on a particular choice of objective and constraints. We argue that algorithms generated by this framework retain many of the desirable characteristics of BEDS while being compatible with a wide range of objectives and constraints."
        }
    ],
    "authoraffiliation": [
        {
            "start": 293,
            "end": 390,
            "text": "Department of Management Science and Engineering\nStanford University\nVia Ortega94305StanfordCAUSA"
        },
        {
            "start": 392,
            "end": 497,
            "text": "Clinical Excellence Research Center\nStanford University School of Medicine\nCampus Drive94305StanfordCAUSA"
        },
        {
            "start": 499,
            "end": 590,
            "text": "Department of Pediatrics\nStanford University School of Medicine\nWelch Rd94304Palo AltoCAUSA"
        },
        {
            "start": 592,
            "end": 674,
            "text": "Lucile Packard Children's Hospital\nStanford University\nWelch Rd94304Palo AltoCAUSA"
        },
        {
            "start": 693,
            "end": 790,
            "text": "Department of Management Science and Engineering\nStanford University\nVia Ortega94305StanfordCAUSA"
        },
        {
            "start": 792,
            "end": 897,
            "text": "Clinical Excellence Research Center\nStanford University School of Medicine\nCampus Drive94305StanfordCAUSA"
        },
        {
            "start": 899,
            "end": 990,
            "text": "Department of Pediatrics\nStanford University School of Medicine\nWelch Rd94304Palo AltoCAUSA"
        },
        {
            "start": 993,
            "end": 1098,
            "text": "Institute for Computational and Mathematical Engineering\nStanford University\nVia Ortega94305StanfordCAUSA"
        }
    ],
    "author": [
        {
            "start": 123,
            "end": 130,
            "text": "Jin Xie"
        },
        {
            "start": 135,
            "end": 145,
            "text": "Teng Zhang"
        },
        {
            "start": 169,
            "end": 182,
            "text": "Jose Blanchet"
        },
        {
            "start": 211,
            "end": 222,
            "text": "Peter Glynn"
        }
    ],
    "email": [
        {
            "start": 146,
            "end": 164,
            "text": "tengz@stanford.edu"
        },
        {
            "start": 183,
            "end": 209,
            "text": "jose.blanchet@stanford.edu"
        },
        {
            "start": 223,
            "end": 241,
            "text": "glynn@stanford.edu"
        },
        {
            "start": 260,
            "end": 291,
            "text": "mrandolph@stanfordchildrens.org"
        }
    ],
    "doi": [
        {
            "start": 61777,
            "end": 61804,
            "text": "10.1001/jama.2018.1150JAMA."
        },
        {
            "start": 61968,
            "end": 61990,
            "text": "10.1001/jama.2018.1150"
        },
        {
            "start": 62012,
            "end": 62034,
            "text": "10.1001/jama.2018.1150"
        }
    ],
    "date": [
        {
            "start": 28689,
            "end": 28699,
            "text": "2018-01-01"
        },
        {
            "start": 28703,
            "end": 28713,
            "text": "2018-12-31"
        },
        {
            "start": 29613,
            "end": 29623,
            "text": "2020-07-27"
        },
        {
            "start": 30691,
            "end": 30701,
            "text": "2019-03-11"
        },
        {
            "start": 30730,
            "end": 30740,
            "text": "2019-03-27"
        },
        {
            "start": 30894,
            "end": 30904,
            "text": "2019-06-28"
        },
        {
            "start": 30933,
            "end": 30943,
            "text": "2019-07-10"
        },
        {
            "start": 34389,
            "end": 34399,
            "text": "2020-07-27"
        },
        {
            "start": 51056,
            "end": 51066,
            "text": "2018-01-01"
        },
        {
            "start": 51175,
            "end": 51185,
            "text": "2017-01-01"
        },
        {
            "start": 53321,
            "end": 53331,
            "text": "2015-02-08"
        },
        {
            "start": 53399,
            "end": 53409,
            "text": "2015-02-08"
        },
        {
            "start": 53536,
            "end": 53546,
            "text": "2015-02-01"
        },
        {
            "start": 53548,
            "end": 53558,
            "text": "2015-02-07"
        },
        {
            "start": 54108,
            "end": 54118,
            "text": "2020-07-27"
        },
        {
            "start": 54139,
            "end": 54149,
            "text": "2019-01-01"
        },
        {
            "start": 56712,
            "end": 56722,
            "text": "2001-01-01"
        },
        {
            "start": 57194,
            "end": 57204,
            "text": "3018-02-22"
        },
        {
            "start": 57228,
            "end": 57238,
            "text": "3018-04-01"
        },
        {
            "start": 57265,
            "end": 57275,
            "text": "3018-02-23"
        },
        {
            "start": 57283,
            "end": 57293,
            "text": "3018-05-27"
        },
        {
            "start": 57384,
            "end": 57394,
            "text": "3018-04-10"
        }
    ],
    "link": [
        {
            "start": 23669,
            "end": 23684,
            "text": "https://github."
        },
        {
            "start": 61996,
            "end": 62035,
            "text": "https://doi.org/10.1001/jama.2018.1150,"
        },
        {
            "start": 62036,
            "end": 62078,
            "text": "https://arxiv.org/abs/https://jamanetwork."
        }
    ]
}